RAM/RAM.v
module ram(

input [7:0] data_in_a, data_in_b,   
input [5:0] addr_a, addr_b,         
input re_a, re_b, we_a, we_b, cs, clk, rst,  
output reg [7:0] data_out_a, data_out_b); 

reg [7:0] data[127:0];  
integer i; 

always @(posedge clk or posedge rst) begin
    if (rst) begin
        for (i = 0; i < 128; i = i + 1) begin
            data[i] <= 8'b0;
        end
    end else if (cs) begin
        if (we_a) begin
            data[addr_a] <= data_in_a;  
        end
        if (we_b) begin
            data[addr_b] <= data_in_b; 
        end

        if (re_a) begin
            data_out_a <= data[addr_a];  
        end
        if (re_b) begin
            data_out_b <= data[addr_b]; 
        end
    end
end

endmodule

RAM/RAMtb.v
`include "RAM.v"
module tb_ram;

  // Testbench signals
  reg [7:0] data_in_a, data_in_b;
  reg [5:0] addr_a, addr_b;
  reg re_a, re_b, we_a, we_b, cs, clk, rst;
  wire [7:0] data_out_a, data_out_b;

    // Instantiate the RAM module (uut stands for Unit Under Test)
  ram uut (
        .data_in_a(data_in_a),
        .data_in_b(data_in_b),
        .addr_a(addr_a),
        .addr_b(addr_b),
        .re_a(re_a),
        .re_b(re_b),
        .we_a(we_a),
        .we_b(we_b),
        .cs(cs),
        .clk(clk),
        .rst(rst),
        .data_out_a(data_out_a),
        .data_out_b(data_out_b)
  );

  // Clock generation
  always begin
    #5 clk = ~clk;  // 10ns clock period
  end

  // Initial block for stimulus
  initial begin
    $dumpfile("dump.vcd");   // Specifies the VCD file
    $dumpvars(0, tb_ram);     // Dumps all signals in the testbench

    // Initialize signals
    clk = 0;
    rst = 0;
    cs = 1;  // Enable chip select
    re_a = 0;
    re_b = 0;
    we_a = 0;
    we_b = 0;
    addr_a = 6'b0;
    addr_b = 6'b0;
    data_in_a = 8'b0;
    data_in_b = 8'b0;

    // Apply Reset
    #5 rst = 1; // Assert reset for 5 ns
    #10 rst = 0; // Deassert reset after 10 ns

    // Test 1: Write to address 5 on port A and read back
    #10 addr_a = 6'd5; data_in_a = 8'hAA; we_a = 1;  // Write AA to address 5 on port A
    #10 we_a = 0; re_a = 1; // Read from address 5 on port A
    #10 $display("Read from Port A: data_out_a = %h", data_out_a); // Expected: 0xAA

    // Test 2: Write to address 10 on port B and read back
    #10 addr_b = 6'd10; data_in_b = 8'h55; we_b = 1;  // Write 55 to address 10 on port B
    #10 we_b = 0; re_b = 1; // Read from address 10 on port B
    #10 $display("Read from Port B: data_out_b = %h", data_out_b); // Expected: 0x55

    // Test 3: Write to the same address (5) on both ports and check results
    #10 addr_a = 6'd5; data_in_a = 8'hBB; we_a = 1;  // Write BB to address 5 on port A
    #10 addr_b = 6'd5; data_in_b = 8'hCC; we_b = 1;  // Write CC to address 5 on port B
    #10 we_a = 0; we_b = 0; re_a = 1; re_b = 1; // Read from the same address (5) on both ports
    #10 $display("Read from Port A: data_out_a = %h", data_out_a); // Expected: 0xBB (port A wins)
    #10 $display("Read from Port B: data_out_b = %h", data_out_b); // Expected: 0xCC (port B wins)

    // Test 4: Write to different addresses and read them back
    #10 addr_a = 6'd15; data_in_a = 8'hDD; we_a = 1;  // Write DD to address 15 on port A
    #10 addr_b = 6'd20; data_in_b = 8'hEE; we_b = 1;  // Write EE to address 20 on port B
    #10 we_a = 0; we_b = 0; re_a = 1; re_b = 1; // Read from address 15 on port A and 20 on port B
    #10 $display("Read from Port A: data_out_a = %h", data_out_a); // Expected: 0xDD
    #10 $display("Read from Port B: data_out_b = %h", data_out_b); // Expected: 0xEE

    // Test 5: Apply reset and check memory content
    #10 rst = 1; // Assert reset again
    #10 rst = 0; // Deassert reset
    #10 addr_a = 6'd5; re_a = 1; // Check if address 5 has been cleared
    #10 $display("Read from Port A after Reset: data_out_a = %h", data_out_a); // Expected: 0x00
    #10 addr_b = 6'd10; re_b = 1; // Check if address 10 has been cleared
    #10 $display("Read from Port B after Reset: data_out_b = %h", data_out_b); // Expected: 0x00

    // End the simulation
    #10 $finish;
  end

endmodule

RAM/dump.vcd
$date
	Sat Apr 26 15:44:34 2025
$end
$version
	Icarus Verilog
$end
$timescale
	1s
$end
$scope module tb_ram $end
$var wire 8 ! data_out_b [7:0] $end
$var wire 8 " data_out_a [7:0] $end
$var reg 6 # addr_a [5:0] $end
$var reg 6 $ addr_b [5:0] $end
$var reg 1 % clk $end
$var reg 1 & cs $end
$var reg 8 ' data_in_a [7:0] $end
$var reg 8 ( data_in_b [7:0] $end
$var reg 1 ) re_a $end
$var reg 1 * re_b $end
$var reg 1 + rst $end
$var reg 1 , we_a $end
$var reg 1 - we_b $end
$scope module uut $end
$var wire 6 . addr_a [5:0] $end
$var wire 6 / addr_b [5:0] $end
$var wire 1 % clk $end
$var wire 1 & cs $end
$var wire 8 0 data_in_a [7:0] $end
$var wire 8 1 data_in_b [7:0] $end
$var wire 1 ) re_a $end
$var wire 1 * re_b $end
$var wire 1 + rst $end
$var wire 1 , we_a $end
$var wire 1 - we_b $end
$var reg 8 2 data_out_a [7:0] $end
$var reg 8 3 data_out_b [7:0] $end
$var integer 32 4 i [31:0] $end
$upscope $end
$upscope $end
$enddefinitions $end
$comment Show the parameter values. $end
$dumpall
$end
#0
$dumpvars
bx 4
bx 3
bx 2
b0 1
b0 0
b0 /
b0 .
0-
0,
0+
0*
0)
b0 (
b0 '
1&
0%
b0 $
b0 #
bx "
bx !
$end
#5
b10000000 4
1+
1%
#10
0%
#15
1%
0+
#20
0%
#25
1%
1,
b10101010 '
b10101010 0
b101 #
b101 .
#30
0%
#35
b10101010 "
b10101010 2
1%
1)
0,
#40
0%
#45
1%
#50
0%
#55
1%
1-
b1010101 (
b1010101 1
b1010 $
b1010 /
#60
0%
#65
b1010101 !
b1010101 3
1%
1*
0-
#70
0%
#75
1%
#80
0%
#85
1%
1,
b10111011 '
b10111011 0
#90
0%
#95
b10111011 !
b10111011 3
b10111011 "
b10111011 2
1%
1-
b11001100 (
b11001100 1
b101 $
b101 /
#100
0%
#105
b11001100 !
b11001100 3
b11001100 "
b11001100 2
1%
0-
0,
#110
0%
#115
1%
#120
0%
#125
1%
#130
0%
#135
b0 "
b0 2
1%
1,
b11011101 '
b11011101 0
b1111 #
b1111 .
#140
0%
#145
b0 !
b0 3
b11011101 "
b11011101 2
1%
1-
b11101110 (
b11101110 1
b10100 $
b10100 /
#150
0%
#155
b11101110 !
b11101110 3
1%
0-
0,
#160
0%
#165
1%
#170
0%
#175
1%
#180
0%
#185
b10000000 4
1%
1+
#190
0%
#195
b0 !
b0 3
b0 "
b0 2
1%
0+
#200
0%
#205
1%
b101 #
b101 .
#210
0%
#215
1%
#220
0%
#225
1%
b1010 $
b1010 /
