1001 Detector/statem.v
module sequence_detector (
    input clk,
    input rst,
    input a,
    output reg op
);
    // State definitions
    parameter s0 = 2'b00, 
              s1 = 2'b01, 
              s2 = 2'b10, 
              s3 = 2'b11;

    reg [1:0] cs; // Current state 

    always @(posedge clk or posedge rst) begin 
        if (rst) begin
            cs <= s0;    // Reset state to s0
            op <= 0;     // Reset output
        end else begin
            case (cs)
                s0: begin
                    cs <= a ? s1 : s0;
                    op <= 0;
                end
                s1: begin
                    cs <= a ? s1 : s2;
                    op <= 0;
                end
                s2: begin
                    
                    cs <= a ? s1 : s3;
                    op <= 0;
                end
                s3: begin
                    cs <= a ? s1 : s0;
                    op <= a ? 1 : 0; // Detects "1001"
                end
                default: begin
                    cs <= s0;  
                    op <= 0;  
                end
            endcase
        end
    end
endmodule

1001 Detector/statemtb.v
`timescale 1ns/1ps
`include "statem.v"  // Include the module file

module test_sequence_detector;
    reg clk;
    reg rst;
    reg a;
    wire op; 

    // Instantiate the sequence detector (uut: unit under test)
    sequence_detector uut (
        .clk(clk),
        .rst(rst),
        .a(a),
        .op(op)
    );

    // Clock generation (100 MHz clock, period = 10 ns)
    initial begin
        clk = 0;
        forever #5 clk = ~clk; // Toggle clock every 5 ns (100 MHz clock)
    end

    // VCD file generation for waveform visualization
    initial begin
        $dumpfile("sequence_detector.vcd");  // VCD file for waveform output
        $dumpvars(0, test_sequence_detector); // Dump all signals
    end

    // Stimulus generation (apply input sequence)
    initial begin
        rst = 1;       // Assert reset initially
        a = 0;         // Start with input 'a' = 0
        #10 rst = 0;   // Deassert reset after 10 ns

        // Apply input sequence: 1001
        #10 a = 1;
        #10 a = 0;
        #10 a = 0;
        #10 a = 1;

        // Apply another sequence: 1001
        #10 a = 1;
        #10 a = 0;
        #10 a = 0;
        #10 a = 1;

        // Apply a non-matching sequence: 1100
        #10 a = 1;
        #10 a = 1;
        #10 a = 0;
        #10 a = 0;

        #10 $finish;  // End simulation after the sequence is applied
    end
endmodule

1001 Detector/sequence_detector.vcd
$date
	Sun Jan 26 21:27:46 2025
$end
$version
	Icarus Verilog
$end
$timescale
	1ps
$end
$scope module test_sequence_detector $end
$var wire 1 ! op $end
$var reg 1 " a $end
$var reg 1 # clk $end
$var reg 1 $ rst $end
$scope module uut $end
$var wire 1 " a $end
$var wire 1 # clk $end
$var wire 1 $ rst $end
$var parameter 2 % s0 $end
$var parameter 2 & s1 $end
$var parameter 2 ' s2 $end
$var parameter 2 ( s3 $end
$var reg 2 ) cs [1:0] $end
$var reg 1 ! op $end
$upscope $end
$upscope $end
$enddefinitions $end
$comment Show the parameter values. $end
$dumpall
b11 (
b10 '
b1 &
b0 %
$end
#0
$dumpvars
b0 )
1$
0#
0"
0!
$end
#5000
1#
#10000
0#
0$
#15000
1#
#20000
0#
1"
#25000
b1 )
1#
#30000
0#
0"
#35000
b10 )
1#
#40000
0#
#45000
b11 )
1#
#50000
0#
1"
#55000
1!
b1 )
1#
#60000
0#
#65000
0!
1#
#70000
0#
0"
#75000
b10 )
1#
#80000
0#
#85000
b11 )
1#
#90000
0#
1"
#95000
1!
b1 )
1#
#100000
0#
#105000
0!
1#
#110000
0#
#115000
1#
#120000
0#
0"
#125000
b10 )
1#
#130000
0#
#135000
b11 )
1#
